unified_message_relay
