Metadata-Version: 2.1
Name: unified-message-relay
Version: 4.2
Summary: Group Message Forward Framework (supports QQ Telegram Line Discord)
Home-page: https://github.com/jqqqqqqqqqq/UnifiedMessageRelay
Author: Curtis Jiang
License: MIT
Project-URL: Telegram Chat, https://t.me/s/UnifiedMessageRelayDev
Keywords: UMR,UnifiedMessageRelay,Group chat relay,IM,messaging
Platform: UNKNOWN
Classifier: Development Status :: 4 - Beta
Classifier: License :: OSI Approved :: MIT License
Classifier: Intended Audience :: Developers
Classifier: Intended Audience :: End Users/Desktop
Classifier: Programming Language :: Python :: 3 :: Only
Classifier: Programming Language :: Python :: 3.7
Classifier: Topic :: Communications :: Chat
Classifier: Topic :: Software Development :: Libraries :: Application Frameworks
Classifier: Typing :: Typed
Requires-Python: >=3.7
